pg_vtscreen/__init__.py
pg_vtscreen/virtual_screen_manager.py
pg_vtscreen-0.1.0.dist-info/LICENSE
pg_vtscreen-0.1.0.dist-info/METADATA
pg_vtscreen-0.1.0.dist-info/WHEEL
pg_vtscreen-0.1.0.dist-info/top_level.txt
pg_vtscreen-0.1.0.dist-info/RECORD
