Metadata-Version: 2.1
Name: pg-vtscreen
Version: 0.1.0
Summary: A virtual screen manager for Pygame that handles window scaling and fullscreen functionality
Home-page: https://github.com/yourusername/pg_vtscreen
Author: NHSU
Author-email: lxp20100205@126.com
License: UNKNOWN
Platform: UNKNOWN
Classifier: Programming Language :: Python :: 3
Classifier: License :: OSI Approved :: BSD License
Classifier: Operating System :: OS Independent
Classifier: Intended Audience :: Developers
Classifier: Topic :: Games/Entertainment
Classifier: Topic :: Software Development :: Libraries :: pygame
Requires-Python: >=3.6
License-File: LICENSE
Requires-Dist: pygame>=2.0.0
